{
	"A3":{
		"correct": 15,
		"total": 16
	}, 
	"B2":{
		"correct" : 13,
		"total": 32
	},	
	"D4":{
		"correct" : 123,
		"total": 322
	},	
	"G1":{
		"correct" : 133,
		"total": 232
	},	
	"A3#":{
		"correct" : 233,
		"total": 242
	},	
	"B1":{
		"correct" : 233,
		"total": 242
	},	
	"G5":{
		"correct" : 233,
		"total": 242
	},
	"G2":{
		"correct" : 233,
		"total": 242
	},
	"F3":{
		"correct" : 233,
		"total": 242
	},	
	"F3#":{
		"correct" : 233,
		"total": 242
	},
	  "overall": {
	    "correct": 0,
	    "total": 0
	  }
}